ms_stim_analysis/__init__.py
ms_stim_analysis/_version.py
ms_stim_analysis/Analysis/__init__.py
ms_stim_analysis/Analysis/circular_shuffle.py
ms_stim_analysis/Analysis/decoding_tables.py
ms_stim_analysis/Analysis/gamma_analysis.py
ms_stim_analysis/Analysis/lfp_analysis.py
ms_stim_analysis/Analysis/lfp_basics.py
ms_stim_analysis/Analysis/position_analysis.py
ms_stim_analysis/Analysis/spiking_analysis.py
ms_stim_analysis/Analysis/spiking_autocorrelation.py
ms_stim_analysis/Analysis/spiking_autocorrelegram.py
ms_stim_analysis/Analysis/spiking_crosscorrelegram.py
ms_stim_analysis/Analysis/spiking_phase_progression_analysis.py
ms_stim_analysis/Analysis/spiking_place_fields.py
ms_stim_analysis/Analysis/utils.py
ms_stim_analysis/Analysis/EM_fitting/AS_EM_module.py
ms_stim_analysis/Analysis/EM_fitting/FiltersEM.py
ms_stim_analysis/Analysis/EM_fitting/TestEM.py
ms_stim_analysis/AnalysisTables/__init__.py
ms_stim_analysis/AnalysisTables/credible_intervals.py
ms_stim_analysis/AnalysisTables/cross_correlation.py
ms_stim_analysis/AnalysisTables/decoding_tables.py
ms_stim_analysis/AnalysisTables/location_times.py
ms_stim_analysis/AnalysisTables/metadata_helpers.py
ms_stim_analysis/AnalysisTables/ms_dio_event.py
ms_stim_analysis/AnalysisTables/ms_interval.py
ms_stim_analysis/AnalysisTables/ms_opto_stim_protocol.py
ms_stim_analysis/AnalysisTables/ms_statescript_event.py
ms_stim_analysis/AnalysisTables/ms_task_identification.py
ms_stim_analysis/AnalysisTables/ms_task_performance.py
ms_stim_analysis/AnalysisTables/place_fields.py
ms_stim_analysis/AnalysisTables/ripples.py
ms_stim_analysis/AnalysisTables/sequence_compression.py
ms_stim_analysis/AnalysisTables/trial_intervals.py
ms_stim_analysis/AnalysisTables/valid_decode_times.py
ms_stim_analysis/AnalysisTables/Utils/__init__.py
ms_stim_analysis/AnalysisTables/Utils/datajoint_table_helpers.py
ms_stim_analysis/AnalysisTables/Utils/df_helpers.py
ms_stim_analysis/AnalysisTables/Utils/list_helpers.py
ms_stim_analysis-0.1.4.dist-info/METADATA
ms_stim_analysis-0.1.4.dist-info/WHEEL
ms_stim_analysis-0.1.4.dist-info/RECORD
