Metadata-Version: 2.4
Name: ms_stim_analysis
Version: 0.1.4
Project-URL: Homepage, https://github.com/samuelbray32/MS_analysis_sam
Project-URL: Bug Tracker, https://github.com/samuelbray32/MS_analysis_sam/issues
Author-email: Samuel Bray <sam.bray@ucsf.edu>
License: MIT License
Classifier: License :: OSI Approved :: MIT License
Classifier: Operating System :: OS Independent
Classifier: Programming Language :: Python :: 3
Requires-Python: >=3.8
Requires-Dist: matplotlib
Requires-Dist: numpy
Requires-Dist: pandas
Requires-Dist: scikit-learn
Requires-Dist: scipy
Requires-Dist: xarray
Provides-Extra: test
Requires-Dist: black; extra == 'test'
